explorer/__init__.py
explorer/dependencies.R
explorer/dxt.py
explorer/version.py
explorer/plots/backup-space-time.R
explorer/plots/dxt-explorer.png
explorer/plots/index.html
explorer/plots/lustre.R
explorer/plots/operation.R
explorer/plots/overlap.R
explorer/plots/overview.R
explorer/plots/space-time.R
explorer/plots/spatiality.R
explorer/plots/transfer.R
dxt_explorer-0.3.dist-info/LICENSE
dxt_explorer-0.3.dist-info/METADATA
dxt_explorer-0.3.dist-info/WHEEL
dxt_explorer-0.3.dist-info/entry_points.txt
dxt_explorer-0.3.dist-info/top_level.txt
dxt_explorer-0.3.dist-info/RECORD
