Metadata-Version: 2.1
Name: dxt-explorer
Version: 0.3
Summary: DXT Explorer is an interactive web-based log analysis tool to visualize Darshan DXT logs and help understand the I/O behavior.
Home-page: https://github.com/hpc-io/dxt-explorer
Author: Jean Luca Bez, Suren Byna
Author-email: jlbez@lbl.gov, sbyna@lbl.gov
Keywords: dxt-explorer
Classifier: Development Status :: 4 - Beta
Classifier: Environment :: Console
Classifier: Intended Audience :: Developers
Classifier: Intended Audience :: Science/Research
Classifier: License :: Other/Proprietary License
Classifier: Programming Language :: Python :: 3 :: Only
Requires-Python: >=3.6
License-File: LICENSE
Requires-Dist: argparse
Requires-Dist: pandas
